dduk/__init__.py
dduk/__main__.py
dduk/application/__init__.py
dduk/application/__main__.py
dduk/application/application.py
dduk/application/command.py
dduk/application/executetype.py
dduk/application/idetype.py
dduk/application/internaldata.py
dduk/application/internalrepository.py
dduk/application/launcher.py
dduk/application/manifestdata.py
dduk/application/predefinedsymbols.py
dduk/application/preparer.py
dduk/application/testslauncher.py
dduk/application/yamlwrapper.py
dduk_application-0.0.88.dist-info/LICENSE
dduk_application-0.0.88.dist-info/METADATA
dduk_application-0.0.88.dist-info/WHEEL
dduk_application-0.0.88.dist-info/top_level.txt
dduk_application-0.0.88.dist-info/RECORD
