Metadata-Version: 2.1
Name: dduk-application
Version: 0.0.88
Summary: ddukbaek2 application library
Home-page: https://ddukbaek2.com
Author: ddukbaek2
Author-email: ddukbaek2@gmail.com
Classifier: Programming Language :: Python :: 3
Classifier: License :: OSI Approved :: MIT License
Classifier: Operating System :: OS Independent
Requires-Python: >=3.7
License-File: LICENSE
Requires-Dist: debugpy
Requires-Dist: pyyaml
Requires-Dist: dduk-core
Requires-Dist: dduk-utility
